README.rst
dataplugin.py
setup.py
pytest_dataplugin.egg-info/PKG-INFO
pytest_dataplugin.egg-info/SOURCES.txt
pytest_dataplugin.egg-info/dependency_links.txt
pytest_dataplugin.egg-info/entry_points.txt
pytest_dataplugin.egg-info/requires.txt
pytest_dataplugin.egg-info/top_level.txt