Metadata-Version: 1.1
Name: pytest-dataplugin
Version: 0.0.2
Summary: A pytest plugin for managing an archive of test data.
Home-page: https://github.com/dwoz/pytest-dataplugin
Author: Daniel Wozniak
Author-email: dan@woz.io
License: UNKNOWN
Download-URL: https://github.com/dwoz/pytest-dataplugin/archive/0.0.0rc1.tar.gz
Keywords: testing,pytest,plugin,fixture
Platform: UNKNOWN
Classifier: Development Status :: 1 - Planning
Classifier: Intended Audience :: Developers
Classifier: License :: OSI Approved :: MIT License
Classifier: Programming Language :: Python
Classifier: Topic :: Software Development :: Testing
Classifier: Topic :: Utilities
Classifier: Framework :: Pytest
